Metadata-Version: 1.0
Name: SimpleVue
Version: 20210106.6
Summary: SimpleVue
Home-page: https://gitee.com/lijiacai/SimpleVue.git
Author: Lijiacai
Author-email: 1050518702@qq.com
License: MIT License
Keywords: vue,python,pyvue,simplevue
Platform: any
